Workbook

Sheet README
A1: Название проекта:
A2: Анализ продаж супермаркета за 2019 год
A4: Источник данных:
A5: Датасет с GitHub (Supermarket Sales)
A7: Инструменты:
A8: Microsoft Excel
A10: Что сделано:
A11: • Очистка и подготовка данных
A12: • Создание вычисляемых столбцов для переформатирования дат в числа (формулы ЗНАЧЕН, ЕСЛИ, ЕОШ, НАЙТИ и др.)
A13: • 5 сводных таблиц по ключевым срезам: гендер, товары, регионы, филиалы, время
A14: • Визуализация в виде дашборда
A15: • Бизнес-выводы и рекомендации по каждому срезу
... A28: 4. Пик продаж: январь-февраль, часы 13-14 и 18-19

Sheet Raw Data
A1: Invoice ID | B1: Branch | C1: City | D1: Customer type | E1: Gender | F1: Product line | G1: Unit price | H1: Quantity | I1: Tax 5% | J1: Total | K1: Date | L1: Time | M1: Payment | N1: Cogs | O1: Gross margin percentage | P1: Gross income | Q1: Rating | T1: Branch | U1: City | V1: Customer type | W1: Gender | X1: Product line
A2: 750-67-8428 | B2: A | C2: Yangon | D2: Member | E2: Female | F2: Health and beauty | G2: 74.69 | H2: 7 | I2: 26.1415 | J2: 548.9715 | K2: 43586 | L2: 0.54722222 | M2: Ewallet | N2: 522.83 | O2: 4.7619048 | P2: 26.1415 | Q2: 46031 | T2: A | U2: Yangon | V2: Member | W2: Female | X2: Health and beauty
A3: 226-31-3081 | B3: C | C3: Naypyitaw | D3: Normal | E3: Female | F3: Electronic accessories | G3: 15.28 | H3: 5 | I3: 30011 | J3: 80.22 | K3: 43680 | L3: 0.43680556 | M3: Cash | N3: 76.4 | O3: 4.7619048 | P3: 30011 | Q3: 46182 | T3: C | U3: Naypyitaw | V3: Normal | W3: Male | X3: Electronic accessories
A4: 631-41-3108 | B4: A | C4: Yangon | D4: Normal | E4: Male | F4: Home and lifestyle | G4: 46.33 | H4: 7 | I4: 16.2155 | J4: 340.5255 | K4: 43527 | L4: 0.55763889 | M4: Credit card | N4: 324.31 | O4: 4.7619048 | P4: 16.2155 | Q4: 46119 | T4: B | U4: Mandalay | X4: Home and lifestyle
A5: 123-19-1176 | B5: A | C5: Yangon | D5: Member | E5: Male | F5: Health and beauty | G5: 58.22 | H5: 8 | I5: 23.288 | J5: 489.048 | K5: 1/27/2019 | L5: 0.85625 | M5: Ewallet | N5: 465.76 | O5: 4.7619048 | P5: 23.288 | Q5: 46120 | X5: Sports and travel
A6: 373-73-7910 | B6: A | C6: Yangon | D6: Normal | E6: Male | F6: Sports and travel | G6: 86.31 | H6: 7 | I6: 30.2085 | J6: 634.3785 | K6: 43679 | L6: 0.44236111 | M6: Ewallet | N6: 604.17 | O6: 4.7619048 | P6: 30.2085 | Q6: 46086 | X6: Food and beverages
A7: 699-14-3026 | B7: C | C7: Naypyitaw | D7: Normal | E7: Male | F7: Electronic accessories | G7: 85.39 | H7: 7 | I7: 29.8865 | J7: 627.6165 | K7: 3/25/2019 | L7: 0.77083333 | M7: Ewallet | N7: 597.73 | O7: 4.7619048 | P7: 29.8865 | Q7: 46026 | X7: Fashion accessories
A8: 355-53-5943 | B8: A | C8: Yangon | D8: Member | E8: Female | F8: Electronic accessories | G8: 68.84 | H8: 6 | I8: 20.652 | J8: 433.692 | K8: 2/25/2019 | L8: 0.60833333 | M8: Ewallet | N8: 413.04 | O8: 4.7619048 | P8: 20.652 | Q8: 46239
A9: 315-22-5665 | B9: C | C9: Naypyitaw | D9: Normal | E9: Female | F9: Home and lifestyle | G9: 73.56 | H9: 10 | I9: 36.78 | J9: 772.38 | K9: 2/24/2019 | L9: 0.48472222 | M9: Ewallet | N9: 735.6 | O9: 4.7619048 | P9: 36.78 | Q9: 8
A10: 665-32-9167 | B10: A | C10: Yangon | D10: Member | E10: Female | F10: Health and beauty | G10: 36.26 | H10: 2 | I10: 3.626 | J10: 76.146 | K10: 43739 | L10: 0.71875 | M10: Credit card | N10: 72.52 | O10: 4.7619048 | P10: 3.626 | Q10: 46060
A11: 692-92-5582 | B11: B | C11: Mandalay | D11: Member | E11: Female | F11: Food and beverages | G11: 54.84 | H11: 3 | I11: 8.226 | J11: 172.746 | K11: 2/20/2019 | L11: 0.56041667 | M11: Credit card | N11: 164.52 | O11: 4.7619048 | P11: 8.226 | Q11: 46270
A12: 351-62-0822 | B12: B | C12: Mandalay | D12: Member | E12: Female | F12: Fashion accessories | G12: 14.48 | H12: 4 | I12: 2.896 | J12: 60.816 | K12: 43618 | L12: 0.75486111 | M12: Ewallet | N12: 57.92 | O12: 4.7619048 | P12: 2.896 | Q12: 46146
A13: 529-56-3974 | B13: B | C13: Mandalay | D13: Member | E13: Male | F13: Electronic accessories | G13: 25.51 | H13: 4 | I13: 5.102 | J13: 107.142 | K13: 43711 | L13: 0.71041667 | M13: Cash | N13: 102.04 | O13: 4.7619048 | P13: 5.102 | Q13: 46240
A14: 365-64-0515 | B14: A | C14: Yangon | D14: Normal | E14: Female | F14: Electronic accessories | G14: 46.95 | H14: 5 | I14: 27699 | J14: 246.4875 | K14: 43801 | L14: 0.43402778 | M14: Ewallet | N14: 234.75 | O14: 4.7619048 | P14: 27699 | Q14: 46029
A15: 252-56-2699 | B15: A | C15: Yangon | D15: Normal | E15: Male | F15: Food and beverages | G15: 43.19 | H15: 10 | I15: 21.595 | J15: 453.495 | K15: 43648 | L15: 0.7 | M15: Ewallet | N15: 431.9 | O15: 4.7619048 | P15: 21.595 | Q15: 46061
A16: 829-34-3910 | B16: A | C16: Yangon | D16: Normal | E16: Female | F16: Health and beauty | G16: 71.38 | H16: 10 | I16: 35.69 | J16: 749.49 | K16: 3/29/2019 | L16: 0.80625 | M16: Cash | N16: 713.8 | O16: 4.7619048 | P16: 35.69 | Q16: 46208
A17: 299-46-1805 | B17: B | C17: Mandalay | D17: Member | E17: Female | F17: Sports and travel | G17: 93.72 | H17: 6 | I17: 28.116 | J17: 590.436 | K17: 1/15/2019 | L17: 0.67986111 | M17: Cash | N17: 562.32 | O17: 4.7619048 | P17: 28.116 | Q17: 46146
A18: 656-95-9349 | B18: A | C18: Yangon | D18: Member | E18: Female | F18: Health and beauty | G18: 68.93 | H18: 7 | I18: 24.1255 | J18: 506.6355 | K18: 43772 | L18: 0.46041667 | M18: Credit card | N18: 482.51 | O18: 4.7619048 | P18: 24.1255 | Q18: 46177
A19: 765-26-6951 | B19: A | C19: Yangon | D19: Normal | E19: Male | F19: Sports and travel | G19: 72.61 | H19: 6 | I19: 21.783 | J19: 457.443 | K19: 43466 | L19: 0.44375 | M19: Credit card | N19: 435.66 | O19: 4.7619048 | P19: 21.783 | Q19: 46271
A20: 329-62-1586 | B20: A | C20: Yangon | D20: Normal | E20: Male | F20: Food and beverages | G20: 54.67 | H20: 3 | I20: 38565 | J20: 172.2105 | K20: 1/21/2019 | L20: 0.75 | M20: Credit card | N20: 164.01 | O20: 4.7619048 | P20: 38565 | Q20: 46181
A21: 319-50-3348 | B21: B | C21: Mandalay | D21: Normal | E21: Female | F21: Home and lifestyle | G21: 40.3 | H21: 2 | I21: 46085 | J21: 84.63 | K21: 43772 | L21: 0.64583333 | M21: Ewallet | N21: 80.6 | O21: 4.7619048 | P21: 46085 | Q21: 46116
A22: 300-71-4605 | B22: C | C22: Naypyitaw | D22: Member | E22: Male | F22: Electronic accessories | G22: 86.04 | H22: 5 | I22: 21.51 | J22: 451.71 | K22: 2/25/2019 | L22: 0.475 | M22: Ewallet | N22: 430.2 | O22: 4.7619048 | P22: 21.51 | Q22: 46238
A23: 371-85-5789 | B23: B | C23: Mandalay | D23: Normal | E23: Male | F23: Health and beauty | G23: 87.98 | H23: 3 | I23: 13.197 | J23: 277.137 | K23: 43588 | L23: 0.44444444 | M23: Ewallet | N23: 263.94 | O23: 4.7619048 | P23: 13.197 | Q23: 46027
A24: 273-16-6619 | B24: B | C24: Mandalay | D24: Normal | E24: Male | F24: Home and lifestyle | G24: 33.2 | H24: 2 | I24: 11749 | J24: 69.72 | K24: 3/15/2019 | L24: 0.51388889 | M24: Credit card | N24: 66.4 | O24: 4.7619048 | P24: 11749 | Q24: 46116
A25: 636-48-8204 | B25: A | C25: Yangon | D25: Normal | E25: Male | F25: Electronic accessories | G25: 34.56 | H25: 5 | I25: 23590 | J25: 181.44 | K25: 2/17/2019 | L25: 0.46875 | M25: Ewallet | N25: 172.8 | O25: 4.7619048 | P25: 23590 | Q25: 46274
A26: 549-59-1358 | B26: A | C26: Yangon | D26: Member | E26: Male | F26: Sports and travel | G26: 88.63 | H26: 3 | I26: 13.2945 | J26: 279.1845 | K26: 43499 | L26: 0.73333333 | M26: Ewallet | N26: 265.89 | O26: 4.7619048 | P26: 13.2945 | Q26: 6
A27: 227-03-5010 | B27: A | C27: Yangon | D27: Member | E27: Female | F27: Home and lifestyle | G27: 52.59 | H27: 8 | I27: 21.036 | J27: 441.756 | K27: 3/22/2019 | L27: 0.80555556 | M27: Credit card | N27: 420.72 | O27: 4.7619048 | P27: 21.036 | Q27: 46150
A28: 649-29-6775 | B28: B | C28: Mandalay | D28: Normal | E28: Male | F28: Fashion accessories | G28: 33.52 | H28: 1 | I28: 1.676 | J28: 35.196 | K28: 43679 | L28: 0.64652778 | M28: Cash | N28: 33.52 | O28: 4.7619048 | P28: 1.676 | Q28: 46209
A29: 189-17-4241 | B29: A | C29: Yangon | D29: Normal | E29: Female | F29: Fashion accessories | G29: 87.67 | H29: 2 | I29: 8.767 | J29: 184.107 | K29: 43741 | L29: 0.51180556 | M29: Credit card | N29: 175.34 | O29: 4.7619048 | P29: 8.767 | Q29: 46210
A30: 145-94-9061 | B30: B | C30: Mandalay | D30: Normal | E30: Female | F30: Food and beverages | G30: 88.36 | H30: 5 | I30: 46287 | J30: 463.89 | K30: 1/25/2019 | L30: 0.825 | M30: Cash | N30: 441.8 | O30: 4.7619048 | P30: 46287 | Q30: 46182
A31: 848-62-7243 | B31: A | C31: Yangon | D31: Normal | E31: Male | F31: Health and beauty | G31: 24.89 | H31: 9 | I31: 38657 | J31: 235.2105 | K31: 3/15/2019 | L31: 0.65 | M31: Cash | N31: 224.01 | O31: 4.7619048 | P31: 38657 | Q31: 46119
A32: 871-79-8483 | B32: B | C32: Mandalay | D32: Normal | E32: Male | F32: Fashion accessories | G32: 94.13 | H32: 5 | I32: 23.5325 | J32: 494.1825 | K32: 2/25/2019 | L32: 0.81875 | M32: Credit card | N32: 470.65 | O32: 4.7619048 | P32: 23.5325 | Q32: 46238
A33: 149-71-6266 | B33: B | C33: Mandalay | D33: Member | E33: Male | F33: Sports and travel | G33: 78.07 | H33: 9 | I33: 35.1315 | J33: 737.7615 | K33: 1/28/2019 | L33: 0.52986111 | M33: Cash | N33: 702.63 | O33: 4.7619048 | P33: 35.1315 | Q33: 46146
A34: 640-49-2076 | B34: B | C34: Mandalay | D34: Normal | E34: Male | F34: Sports and travel | G34: 83.78 | H34: 8 | I34: 33.512 | J34: 703.752 | K34: 43739 | L34: 0.61736111 | M34: Cash | N34: 670.24 | O34: 4.7619048 | P34: 33.512 | Q34: 46027
A35: 595-11-5460 | B35: A | C35: Yangon | D35: Normal | E35: Male | F35: Health and beauty | G35: 96.58 | H35: 2 | I35: 9.658 | J35: 202.818 | K35: 3/15/2019 | L35: 0.425 | M35: Credit card | N35: 193.16 | O35: 4.7619048 | P35: 9.658 | Q35: 46027
A36: 183-56-6882 | B36: C | C36: Naypyitaw | D36: Member | E36: Female | F36: Food and beverages | G36: 99.42 | H36: 4 | I36: 19.884 | J36: 417.564 | K36: 43618 | L36: 0.44583333 | M36: Ewallet | N36: 397.68 | O36: 4.7619048 | P36: 19.884 | Q36: 46149
A37: 232-16-2483 | B37: C | C37: Naypyitaw | D37: Member | E37: Female | F37: Sports and travel | G37: 68.12 | H37: 1 | I37: 3.406 | J37: 71.526 | K37: 43647 | L37: 0.51944444 | M37: Ewallet | N37: 68.12 | O37: 4.7619048 | P37: 3.406 | Q37: 46240
A38: 129-29-8530 | B38: A | C38: Yangon | D38: Member | E38: Male | F38: Sports and travel | G38: 62.62 | H38: 5 | I38: 15.655 | J38: 328.755 | K38: 43741 | L38: 0.80208333 | M38: Ewallet | N38: 313.1 | O38: 4.7619048 | P38: 15.655 | Q38: 7
A39: 272-65-1806 | B39: A | C39: Yangon | D39: Normal | E39: Female | F39: Electronic accessories | G39: 60.88 | H39: 9 | I39: 27.396 | J39: 575.316 | K39: 1/15/2019 | L39: 0.72013889 | M39: Ewallet | N39: 547.92 | O39: 4.7619048 | P39: 27.396 | Q39: 46207
A40: 333-73-7901 | B40: C | C40: Naypyitaw | D40: Normal | E40: Female | F40: Health and beauty | G40: 54.92 | H40: 8 | I40: 21.968 | J40: 461.328 | K40: 3/23/2019 | L40: 0.55833333 | M40: Ewallet | N40: 439.36 | O40: 4.7619048 | P40: 21.968 | Q40: 46180
A41: 777-82-7220 | B41: B | C41: Mandalay | D41: Member | E41: Male | F41: Home and lifestyle | G41: 46386 | H41: 8 | I41: 12.048 | J41: 253.008 | K41: 43527 | L41: 0.54236111 | M41: Cash | N41: 240.96 | O41: 4.7619048 | P41: 12.048 | Q41: 46210
A42: 280-35-5823 | B42: B | C42: Mandalay | D42: Member | E42: Female | F42: Home and lifestyle | G42: 86.72 | H42: 1 | I42: 4.336 | J42: 91.056 | K42: 1/17/2019 | L42: 0.78125 | M42: Ewallet | N42: 86.72 | O42: 4.7619048 | P42: 4.336 | Q42: 46272
A43: 554-53-8700 | B43: C | C43: Naypyitaw | D43: Member | E43: Male | F43: Home and lifestyle | G43: 56.11 | H43: 2 | I43: 5.611 | J43: 117.831 | K43: 43498 | L43: 0.42430556 | M43: Cash | N43: 112.22 | O43: 4.7619048 | P43: 5.611 | Q43: 46087
A44: 354-25-5821 | B44: B | C44: Mandalay | D44: Member | E44: Female | F44: Sports and travel | G44: 69.12 | H44: 6 | I44: 20.736 | J44: 435.456 | K44: 43679 | L44: 0.54375 | M44: Cash | N44: 414.72 | O44: 4.7619048 | P44: 20.736 | Q44: 46178
A45: 228-96-1411 | B45: C | C45: Naypyitaw | D45: Member | E45: Female | F45: Food and beverages | G45: 98.7 | H45: 8 | I45: 39.48 | J45: 829.08 | K45: 43558 | L45: 0.86041667 | M45: Cash | N45: 789.6 | O45: 4.7619048 | P45: 39.48 | Q45: 46180
A46: 617-15-4209 | B46: C | C46: Naypyitaw | D46: Member | E46: Male | F46: Health and beauty | G46: 15.37 | H46: 2 | I46: 1.537 | J46: 32.277 | K46: 3/16/2019 | L46: 0.82430556 | M46: Cash | N46: 30.74 | O46: 4.7619048 | P46: 1.537 | Q46: 46060
A47: 132-32-9879 | B47: B | C47: Mandalay | D47: Member | E47: Female | F47: Electronic accessories | G47: 93.96 | H47: 4 | I47: 18.792 | J47: 394.632 | K47: 43711 | L47: 0.75 | M47: Cash | N47: 375.84 | O47: 4.7619048 | P47: 18.792 | Q47: 46151
A48: 370-41-7321 | B48: B | C48: Mandalay | D48: Member | E48: Male | F48: Health and beauty | G48: 56.69 | H48: 9 | I48: 25.5105 | J48: 535.7205 | K48: 2/27/2019 | L48: 0.725 | M48: Credit card | N48: 510.21 | O48: 4.7619048 | P48: 25.5105 | Q48: 46120
A49: 727-46-3608 | B49: B | C49: Mandalay | D49: Member | E49: Female | F49: Food and beverages | G49: 46042 | H49: 9 | I49: 9.0045 | J49: 189.0945 | K49: 43618 | L49: 0.65763889 | M49: Ewallet | N49: 180.09 | O49: 4.7619048 | P49: 9.0045 | Q49: 46026
A50: 669-54-1719 | B50: B | C50: Mandalay | D50: Member | E50: Male | F50: Electronic accessories | G50: 18.93 | H50: 6 | I50: 5.679 | J50: 119.259 | K50: 43740 | L50: 0.53125 | M50: Credit card | N50: 113.58 | O50: 4.7619048 | P50: 5.679 | Q50: 46030
A51: 574-22-5561 | B51: C | C51: Naypyitaw | D51: Member | E51: Female | F51: Fashion accessories | G51: 82.63 | H51: 10 | I51: 41.315 | J51: 867.615 | K51: 3/19/2019 | L51: 0.71388889 | M51: Ewallet | N51: 826.3 | O51: 4.7619048 | P51: 41.315 | Q51: 46272
A52: 326-78-5178 | B52: C | C52: Naypyitaw | D52: Member | E52: Male | F52: Food and beverages | G52: 91.4 | H52: 7 | I52: 31.99 | J52: 671.79 | K52: 43526 | L52: 0.42986111 | M52: Cash | N52: 639.8 | O52: 4.7619048 | P52: 31.99 | Q52: 46151
A53: 162-48-8011 | B53: A | C53: Yangon | D53: Member | E53: Female | F53: Food and beverages | G53: 44.59 | H53: 5 | I53: 11.1475 | J53: 234.0975 | K53: 43740 | L53: 0.63194444 | M53: Cash | N53: 222.95 | O53: 4.7619048 | P53: 11.1475 | Q53: 46150
A54: 616-24-2851 | B54: B | C54: Mandalay | D54: Member | E54: Female | F54: Fashion accessories | G54: 17.87 | H54: 4 | I54: 3.574 | J54: 75.054 | K54: 3/22/2019 | L54: 0.6125 | M54: Ewallet | N54: 71.48 | O54: 4.7619048 | P54: 3.574 | Q54: 46148
A55: 778-71-5554 | B55: C | C55: Naypyitaw | D55: Member | E55: Male | F55: Fashion accessories | G55: 15.43 | H55: 1 | I55: 0.7715 | J55: 16.2015 | K55: 1/25/2019 | L55: 0.65694444 | M55: Credit card | N55: 15.43 | O55: 4.7619048 | P55: 0.7715 | Q55: 46028
A56: 242-55-6721 | B56: B | C56: Mandalay | D56: Normal | E56: Male | F56: Home and lifestyle | G56: 16.16 | H56: 2 | I56: 1.616 | J56: 33.936 | K56: 43649 | L56: 0.49236111 | M56: Ewallet | N56: 32.32 | O56: 4.7619048 | P56: 1.616 | Q56: 46148
A57: 399-46-5918 | B57: C | C57: Naypyitaw | D57: Normal | E57: Female | F57: Electronic accessories | G57: 85.98 | H57: 8 | I57: 34.392 | J57: 722.232 | K57: 2/28/2019 | L57: 0.79236111 | M57: Cash | N57: 687.84 | O57: 4.7619048 | P57: 34.392 | Q57: 46061
A58: 106-35-6779 | B58: A | C58: Yangon | D58: Member | E58: Male | F58: Home and lifestyle | G58: 44.34 | H58: 2 | I58: 4.434 | J58: 93.114 | K58: 3/27/2019 | L58: 0.47638889 | M58: Cash | N58: 88.68 | O58: 4.7619048 | P58: 4.434 | Q58: 46239
A59: 635-40-6220 | B59: A | C59: Yangon | D59: Normal | E59: Male | F59: Health and beauty | G59: 89.6 | H59: 8 | I59: 35.84 | J59: 752.64 | K59: 43648 | L59: 0.47777778 | M59: Ewallet | N59: 716.8 | O59: 4.7619048 | P59: 35.84 | Q59: 46179
A60: 817-48-8732 | B60: A | C60: Yangon | D60: Member | E60: Female | F60: Home and lifestyle | G60: 72.35 | H60: 10 | I60: 36.175 | J60: 759.675 | K60: 1/20/2019 | L60: 0.66319444 | M60: Cash | N60: 723.5 | O60: 4.7619048 | P60: 36.175 | Q60: 46117
A61: 120-06-4233 | B61: C | C61: Naypyitaw | D61: Normal | E61: Male | F61: Electronic accessories | G61: 30.61 | H61: 6 | I61: 9.183 | J61: 192.843 | K61: 43802 | L61: 0.85833333 | M61: Cash | N61: 183.66 | O61: 4.7619048 | P61: 9.183 | Q61: 46090
A62: 285-68-5083 | B62: C | C62: Naypyitaw | D62: Member | E62: Female | F62: Sports and travel | G62: 24.74 | H62: 3 | I62: 3.711 | J62: 77.931 | K62: 2/15/2019 | L62: 0.74097222 | M62: Credit card | N62: 74.22 | O62: 4.7619048 | P62: 3.711 | Q62: 10
A63: 803-83-5989 | B63: C | C63: Naypyitaw | D63: Normal | E63: Male | F63: Home and lifestyle | G63: 55.73 | H63: 6 | I63: 16.719 | J63: 351.099 | K63: 2/24/2019 | L63: 0.45486111 | M63: Ewallet | N63: 334.38 | O63: 4.7619048 | P63: 16.719 | Q63: 7
A64: 347-34-2234 | B64: B | C64: Mandalay | D64: Member | E64: Female | F64: Sports and travel | G64: 55.07 | H64: 9 | I64: 24.7815 | J64: 520.4115 | K64: 43526 | L64: 0.56944444 | M64: Ewallet | N64: 495.63 | O64: 4.7619048 | P64: 24.7815 | Q64: 10
A65: 199-75-8169 | B65: A | C65: Yangon | D65: Member | E65: Male | F65: Sports and travel | G65: 15.81 | H65: 10 | I65: 7.905 | J65: 166.005 | K65: 43619 | L65: 0.51875 | M65: Credit card | N65: 158.1 | O65: 4.7619048 | P65: 7.905 | Q65: 46181
A66: 853-23-2453 | B66: B | C66: Mandalay | D66: Member | E66: Male | F66: Health and beauty | G66: 75.74 | H66: 4 | I66: 15.148 | J66: 318.108 | K66: 2/14/2019 | L66: 0.60763889 | M66: Cash | N66: 302.96 | O66: 4.7619048 | P66: 15.148 | Q66: 46180
A67: 877-22-3308 | B67: A | C67: Yangon | D67: Member | E67: Male | F67: Health and beauty | G67: 15.87 | H67: 10 | I67: 7.935 | J67: 166.635 | K67: 3/13/2019 | L67: 0.69444444 | M67: Cash | N67: 158.7 | O67: 4.7619048 | P67: 7.935 | Q67: 46239
A68: 838-78-4295 | B68: C | C68: Naypyitaw | D68: Normal | E68: Female | F68: Health and beauty | G68: 33.47 | H68: 2 | I68: 3.347 | J68: 70.287 | K68: 43740 | L68: 0.65486111 | M68: Ewallet | N68: 66.94 | O68: 4.7619048 | P68: 3.347 | Q68: 46209
A69: 109-28-2512 | B69: B | C69: Mandalay | D69: Member | E69: Female | F69: Fashion accessories | G69: 97.61 | H69: 6 | I69: 29.283 | J69: 614.943 | K69: 43647 | L69: 0.62569444 | M69: Ewallet | N69: 585.66 | O69: 4.7619048 | P69: 29.283 | Q69: 46274
A70: 232-11-3025 | B70: A | C70: Yangon | D70: Normal | E70: Male | F70: Sports and travel | G70: 78.77 | H70: 10 | I70: 39.385 | J70: 827.085 | K70: 1/24/2019 | L70: 0.41944444 | M70: Cash | N70: 787.7 | O70: 4.7619048 | P70: 39.385 | Q70: 46118
A71: 382-03-4532 | B71: A | C71: Yangon | D71: Member | E71: Female | F71: Health and beauty | G71: 18.33 | H71: 1 | I71: 0.9165 | J71: 19.2465 | K71: 43498 | L71: 0.78472222 | M71: Cash | N71: 18.33 | O71: 4.7619048 | P71: 0.9165 | Q71: 46085
A72: 393-65-2792 | B72: C | C72: Naypyitaw | D72: Normal | E72: Male | F72: Food and beverages | G72: 89.48 | H72: 10 | I72: 44.74 | J72: 939.54 | K72: 43617 | L72: 0.53194444 | M72: Credit card | N72: 894.8 | O72: 4.7619048 | P72: 44.74 | Q72: 46182
A73: 796-12-2025 | B73: C | C73: Naypyitaw | D73: Normal | E73: Male | F73: Fashion accessories | G73: 62.12 | H73: 10 | I73: 31.06 | J73: 652.26 | K73: 43771 | L73: 0.67986111 | M73: Cash | N73: 621.2 | O73: 4.7619048 | P73: 31.06 | Q73: 46270
A74: 510-95-6347 | B74: B | C74: Mandalay | D74: Member | E74: Female | F74: Food and beverages | G74: 48.52 | H74: 3 | I74: 7.278 | J74: 152.838 | K74: 43588 | L74: 0.76180556 | M74: Ewallet | N74: 145.56 | O74: 4.7619048 | P74: 7.278 | Q74: 4
A75: 841-35-6630 | B75: C | C75: Naypyitaw | D75: Normal | E75: Female | F75: Electronic accessories | G75: 75.91 | H75: 6 | I75: 22.773 | J75: 478.233 | K75: 43711 | L75: 0.76458333 | M75: Cash | N75: 455.46 | O75: 4.7619048 | P75: 22.773 | Q75: 46211
A76: 287-21-9091 | B76: A | C76: Yangon | D76: Normal | E76: Male | F76: Home and lifestyle | G76: 74.67 | H76: 9 | I76: 33.6015 | J76: 705.6315 | K76: 1/22/2019 | L76: 0.45486111 | M76: Ewallet | N76: 672.03 | O76: 4.7619048 | P76: 33.6015 | Q76: 46121
A77: 732-94-0499 | B77: C | C77: Naypyitaw | D77: Normal | E77: Female | F77: Electronic accessories | G77: 41.65 | H77: 10 | I77: 20.825 | J77: 437.325 | K77: 1/13/2019 | L77: 0.71111111 | M77: Credit card | N77: 416.5 | O77: 4.7619048 | P77: 20.825 | Q77: 46117
A78: 263-10-3913 | B78: C | C78: Naypyitaw | D78: Member | E78: Male | F78: Fashion accessories | G78: 49.04 | H78: 9 | I78: 22.068 | J78: 463.428 | K78: 43709 | L78: 0.59722222 | M78: Credit card | N78: 441.36 | O78: 4.7619048 | P78: 22.068 | Q78: 46181
A79: 381-20-0914 | B79: A | C79: Yangon | D79: Member | E79: Female | F79: Fashion accessories | G79: 46042 | H79: 9 | I79: 9.0045 | J79: 189.0945 | K79: 43800 | L79: 0.65833333 | M79: Credit card | N79: 180.09 | O79: 4.7619048 | P79: 9.0045 | Q79: 46208
A80: 829-49-1914 | B80: C | C80: Naypyitaw | D80: Member | E80: Female | F80: Food and beverages | G80: 78.31 | H80: 10 | I80: 39.155 | J80: 822.255 | K80: 43588 | L80: 0.68333333 | M80: Ewallet | N80: 783.1 | O80: 4.7619048 | P80: 39.155 | Q80: 46179
A81: 756-01-7507 | B81: C | C81: Naypyitaw | D81: Normal | E81: Female | F81: Health and beauty | G81: 20.38 | H81: 5 | I81: 5.095 | J81: 106.995 | K81: 1/22/2019 | L81: 0.78888889 | M81: Cash | N81: 101.9 | O81: 4.7619048 | P81: 5.095 | Q81: 6
A82: 870-72-4431 | B82: C | C82: Naypyitaw | D82: Normal | E82: Female | F82: Health and beauty | G82: 99.19 | H82: 6 | I82: 29.757 | J82: 624.897 | K82: 1/21/2019 | L82: 0.6125 | M82: Credit card | N82: 595.14 | O82: 4.7619048 | P82: 29.757 | Q82: 46147
A83: 847-38-7188 | B83: B | C83: Mandalay | D83: Normal | E83: Female | F83: Food and beverages | G83: 96.68 | H83: 3 | I83: 14.502 | J83: 304.542 | K83: 1/26/2019 | L83: 0.83055556 | M83: Ewallet | N83: 290.04 | O83: 4.7619048 | P83: 14.502 | Q83: 46118
A84: 480-63-2856 | B84: C | C84: Naypyitaw | D84: Normal | E84: Male | F84: Food and beverages | G84: 19.25 | H84: 8 | I84: 46210 | J84: 161.7 | K84: 1/23/2019 | L84: 0.77569444 | M84: Ewallet | N84: 154 | O84: 4.7619048 | P84: 46210 | Q84: 46179
A85: 787-56-0757 | B85: C | C85: Naypyitaw | D85: Member | E85: Female | F85: Food and beverages | G85: 80.36 | H85: 4 | I85: 16.072 | J85: 337.512 | K85: 2/23/2019 | L85: 0.78125 | M85: Credit card | N85: 321.44 | O85: 4.7619048 | P85: 16.072 | Q85: 46089
A86: 360-39-5055 | B86: C | C86: Naypyitaw | D86: Member | E86: Male | F86: Sports and travel | G86: 48.91 | H86: 5 | I86: 27729 | J86: 256.7775 | K86: 43711 | L86: 0.42847222 | M86: Cash | N86: 244.55 | O86: 4.7619048 | P86: 27729 | Q86: 46179
A87: 730-50-9884 | B87: C | C87: Naypyitaw | D87: Normal | E87: Female | F87: Sports and travel | G87: 83.06 | H87: 7 | I87: 29.071 | J87: 610.491 | K87: 43588 | L87: 0.60486111 | M87: Ewallet | N87: 581.42 | O87: 4.7619048 | P87: 29.071 | Q87: 4
A88: 362-58-8315 | B88: C | C88: Naypyitaw | D88: Normal | E88: Male | F88: Fashion accessories | G88: 76.52 | H88: 5 | I88: 19.13 | J88: 401.73 | K88: 3/25/2019 | L88: 0.43263889 | M88: Cash | N88: 382.6 | O88: 4.7619048 | P88: 19.13 | Q88: 46274
A89: 633-44-8566 | B89: A | C89: Yangon | D89: Member | E89: Male | F89: Food and beverages | G89: 49.38 | H89: 7 | I89: 17.283 | J89: 362.943 | K89: 3/27/2019 | L89: 0.85763889 | M89: Credit card | N89: 345.66 | O89: 4.7619048 | P89: 17.283 | Q89: 46088
A90: 504-35-8843 | B90: A | C90: Yangon | D90: Normal | E90: Male | F90: Sports and travel | G90: 42.47 | H90: 1 | I90: 2.1235 | J90: 44.5935 | K90: 43497 | L90: 0.70625 | M90: Cash | N90: 42.47 | O90: 4.7619048 | P90: 2.1235 | Q90: 46208
A91: 318-68-5053 | B91: B | C91: Mandalay | D91: Normal | E91: Female | F91: Health and beauty | G91: 76.99 | H91: 6 | I91: 23.097 | J91: 485.037 | K91: 2/27/2019 | L91: 0.74652778 | M91: Cash | N91: 461.94 | O91: 4.7619048 | P91: 23.097 | Q91: 46028
A92: 565-80-5980 | B92: C | C92: Naypyitaw | D92: Member | E92: Female | F92: Home and lifestyle | G92: 47.38 | H92: 4 | I92: 9.476 | J92: 198.996 | K92: 1/23/2019 | L92: 0.43402778 | M92: Cash | N92: 189.52 | O92: 4.7619048 | P92: 9.476 | Q92: 46029
A93: 225-32-0908 | B93: C | C93: Naypyitaw | D93: Normal | E93: Female | F93: Sports and travel | G93: 44.86 | H93: 10 | I93: 22.43 | J93: 471.03 | K93: 1/26/2019 | L93: 0.82916667 | M93: Ewallet | N93: 448.6 | O93: 4.7619048 | P93: 22.43 | Q93: 46061
A94: 873-51-0671 | B94: A | C94: Yangon | D94: Member | E94: Female | F94: Sports and travel | G94: 21.98 | H94: 7 | I94: 7.693 | J94: 161.553 | K94: 43739 | L94: 0.69583333 | M94: Ewallet | N94: 153.86 | O94: 4.7619048 | P94: 7.693 | Q94: 46027
A95: 152-08-9985 | B95: B | C95: Mandalay | D95: Member | E95: Male | F95: Health and beauty | G95: 64.36 | H95: 9 | I95: 28.962 | J95: 608.202 | K95: 43802 | L95: 0.50625 | M95: Credit card | N95: 579.24 | O95: 4.7619048 | P95: 28.962 | Q95: 46181
A96: 512-91-0811 | B96: C | C96: Naypyitaw | D96: Normal | E96: Male | F96: Health and beauty | G96: 89.75 | H96: 1 | I96: 27485 | J96: 94.2375 | K96: 43618 | L96: 0.83680556 | M96: Credit card | N96: 89.75 | O96: 4.7619048 | P96: 27485 | Q96: 46179
A97: 594-34-4444 | B97: A | C97: Yangon | D97: Normal | E97: Male | F97: Electronic accessories | G97: 97.16 | H97: 1 | I97: 4.858 | J97: 102.018 | K97: 43680 | L97: 0.85972222 | M97: Ewallet | N97: 97.16 | O97: 4.7619048 | P97: 4.858 | Q97: 46060
A98: 766-85-7061 | B98: B | C98: Mandalay | D98: Normal | E98: Male | F98: Health and beauty | G98: 87.87 | H98: 10 | I98: 43.935 | J98: 922.635 | K98: 3/29/2019 | L98: 0.43402778 | M98: Ewallet | N98: 878.7 | O98: 4.7619048 | P98: 43.935 | Q98: 46027
A99: 871-39-9221 | B99: C | C99: Naypyitaw | D99: Normal | E99: Female | F99: Electronic accessories | G99: 16772 | H99: 6 | I99: 3.735 | J99: 78.435 | K99: 43710 | L99: 0.54930556 | M99: Cash | N99: 74.7 | O99: 4.7619048 | P99: 3.735 | Q99: 46026
A100: 865-92-6136 | B100: A | C100: Yangon | D100: Normal | E100: Male | F100: Food and beverages | G100: 52.75 | H100: 3 | I100: 45839 | J100: 166.1625 | K100: 3/23/2019 | L100: 0.42777778 | M100: Ewallet | N100: 158.25 | O100: 4.7619048 | P100: 45839 | Q100: 46090
...

Sheet Cleaned Data
A1: Invoice ID | B1: Branch | C1: City | D1: Customer type | E1: Gender | F1: Product line | G1: Unit price | H1: Quantity | I1: Tax 5% | J1: Total | K1: Date | L1: Time | M1: Payment | N1: Cogs | O1: Gross margin percentage | P1: Gross income | Q1: Rating
A2: 750-67-8428 | B2: A | C2: Yangon | D2: Member | E2: Female | F2: Health and beauty | G2: =VALUE(IF(AND(ISERR(FIND(".",'Raw Data'!G2)),LEN('Raw Data'!G2)=5), IF(YEAR('Raw Data'!G2)=2026,CONCATENATE(DAY('Raw Data'!G2),".",IF(LEN(MONTH('Raw Data'!G2))=2,MONTH('Raw Data'!G2),CONCATENATE("0",MONTH('Raw Data'!G2)))),CONCATENATE(MONTH('Raw Data'!G2),".",RIGHT(YEAR('Raw Data'!G2),2))),'Raw Data'!G2)) -> 74.69 | H2: ='Raw Data'!H2 -> 7 | I2: =J2-G2*H2 -> 26.1415 | J2: ='Raw Data'!J2 -> 548.9715 | K2: =VALUE(IFERROR(VALUE('Raw Data'!K2),CONCATENATE(MID('Raw Data'!K2,3,2),".","0",LEFT('Raw Data'!K2,1),".", RIGHT('Raw Data'!K2,4)))) -> 43586 | L2: ='Raw Data'!L2 -> 0.54722222 | M2: Ewallet | N2: =VALUE(IF(AND(ISERR(FIND(".",'Raw Data'!N2)),LEN('Raw Data'!N2)=5), IF(YEAR('Raw Data'!N2)=2026,CONCATENATE(DAY('Raw Data'!N2),".",IF(LEN(MONTH('Raw Data'!N2))=2,MONTH('Raw Data'!N2),CONCATENATE("0",MONTH('Raw Data'!N2)))),CONCATENATE(MONTH('Raw Data'!N2),".",RIGHT(YEAR('Raw Data'!N2),2))),'Raw Data'!N2)) -> 522.83 | O2: =P2/J2*100 -> 4.7619048 | P2: =J2-N2 -> 26.1415 | Q2: =VALUE(IF(AND(ISERR(FIND(".",'Raw Data'!Q2)),LEN('Raw Data'!Q2)=5), IF(YEAR('Raw Data'!Q2)=2026,CONCATENATE(DAY('Raw Data'!Q2),".",IF(LEN(MONTH('Raw Data'!Q2))=2,MONTH('Raw Data'!Q2),CONCATENATE(MONTH('Raw Data'!Q2)))),CONCATENATE(MONTH('Raw Data'!Q2),".",RIGHT(YEAR('Raw Data'!Q2),2))),'Raw Data'!Q2)) -> 9.1
A3: 226-31-3081 | B3: C | C3: Naypyitaw | D3: Normal | E3: Female | F3: Electronic accessories | G3: =VALUE(IF(AND(ISERR(FIND(".",'Raw Data'!G3)),LEN('Raw Data'!G3)=5), IF(YEAR('Raw Data'!G3)=2026,CONCATENATE(DAY('Raw Data'!G3),".",IF(LEN(MONTH('Raw Data'!G3))=2,MONTH('Raw Data'!G3),CONCATENATE("0",MONTH('Raw Data'!G3)))),CONCATENATE(MONTH('Raw Data'!G3),".",RIGHT(YEAR('Raw Data'!G3),2))),'Raw Data'!G3)) -> 15.28 | H3: ='Raw Data'!H3 -> 5 | I3: =J3-G3*H3 -> 3.82 | J3: ='Raw Data'!J3 -> 80.22 | K3: =VALUE(IFERROR(VALUE('Raw Data'!K3),CONCATENATE(MID('Raw Data'!K3,3,2),".","0",LEFT('Raw Data'!K3,1),".", RIGHT('Raw Data'!K3,4)))) -> 43680 | L3: ='Raw Data'!L3 -> 0.43680556 | M3: Cash | N3: =VALUE(IF(AND(ISERR(FIND(".",'Raw Data'!N3)),LEN('Raw Data'!N3)=5), IF(YEAR('Raw Data'!N3)=2026,CONCATENATE(DAY('Raw Data'!N3),".",IF(LEN(MONTH('Raw Data'!N3))=2,MONTH('Raw Data'!N3),CONCATENATE("0",MONTH('Raw Data'!N3)))),CONCATENATE(MONTH('Raw Data'!N3),".",RIGHT(YEAR('Raw Data'!N3),2))),'Raw Data'!N3)) -> 76.4 | O3: =P3/J3*100 -> 4.7619048 | P3: =J3-N3 -> 3.82 | Q3: =VALUE(IF(AND(ISERR(FIND(".",'Raw Data'!Q3)),LEN('Raw Data'!Q3)=5), IF(YEAR('Raw Data'!Q3)=2026,CONCATENATE(DAY('Raw Data'!Q3),".",IF(LEN(MONTH('Raw Data'!Q3))=2,MONTH('Raw Data'!Q3),CONCATENATE(MONTH('Raw Data'!Q3)))),CONCATENATE(MONTH('Raw Data'!Q3),".",RIGHT(YEAR('Raw Data'!Q3),2))),'Raw Data'!Q3)) -> 9.6
A4: 631-41-3108 | B4: A | C4: Yangon | D4: Normal | E4: Male | F4: Home and lifestyle | G4: =VALUE(IF(AND(ISERR(FIND(".",'Raw Data'!G4)),LEN('Raw Data'!G4)=5), IF(YEAR('Raw Data'!G4)=2026,CONCATENATE(DAY('Raw Data'!G4),".",IF(LEN(MONTH('Raw Data'!G4))=2,MONTH('Raw Data'!G4),CONCATENATE("0",MONTH('Raw Data'!G4)))),CONCATENATE(MONTH('Raw Data'!G4),".",RIGHT(YEAR('Raw Data'!G4),2))),'Raw Data'!G4)) -> 46.33 | H4: ='Raw Data'!H4 -> 7 | I4: =J4-G4*H4 -> 16.2155 | J4: ='Raw Data'!J4 -> 340.5255 | K4: =VALUE(IFERROR(VALUE('Raw Data'!K4),CONCATENATE(MID('Raw Data'!K4,3,2),".","0",LEFT('Raw Data'!K4,1),".", RIGHT('Raw Data'!K4,4)))) -> 43527 | L4: ='Raw Data'!L4 -> 0.55763889 | M4: Credit card | N4: =VALUE(IF(AND(ISERR(FIND(".",'Raw Data'!N4)),LEN('Raw Data'!N4)=5), IF(YEAR('Raw Data'!N4)=2026,CONCATENATE(DAY('Raw Data'!N4),".",IF(LEN(MONTH('Raw Data'!N4))=2,MONTH('Raw Data'!N4),CONCATENATE("0",MONTH('Raw Data'!N4)))),CONCATENATE(MONTH('Raw Data'!N4),".",RIGHT(YEAR('Raw Data'!N4),2))),'Raw Data'!N4)) -> 324.31 | O4: =P4/J4*100 -> 4.7619048 | P4: =J4-N4 -> 16.2155 | Q4: =VALUE(IF(AND(ISERR(FIND(".",'Raw Data'!Q4)),LEN('Raw Data'!Q4)=5), IF(YEAR('Raw Data'!Q4)=2026,CONCATENATE(DAY('Raw Data'!Q4),".",IF(LEN(MONTH('Raw Data'!Q4))=2,MONTH('Raw Data'!Q4),CONCATENATE(MONTH('Raw Data'!Q4)))),CONCATENATE(MONTH('Raw Data'!Q4),".",RIGHT(YEAR('Raw Data'!Q4),2))),'Raw Data'!Q4)) -> 7.4
A5: 123-19-1176 | B5: A | C5: Yangon | D5: Member | E5: Male | F5: Health and beauty | G5: =VALUE(IF(AND(ISERR(FIND(".",'Raw Data'!G5)),LEN('Raw Data'!G5)=5), IF(YEAR('Raw Data'!G5)=2026,CONCATENATE(DAY('Raw Data'!G5),".",IF(LEN(MONTH('Raw Data'!G5))=2,MONTH('Raw Data'!G5),CONCATENATE("0",MONTH('Raw Data'!G5)))),CONCATENATE(MONTH('Raw Data'!G5),".",RIGHT(YEAR('Raw Data'!G5),2))),'Raw Data'!G5)) -> 58.22 | H5: ='Raw Data'!H5 -> 8 | I5: =J5-G5*H5 -> 23.288 | J5: ='Raw Data'!J5 -> 489.048 | K5: =VALUE(IFERROR(VALUE('Raw Data'!K5),CONCATENATE(MID('Raw Data'!K5,3,2),".","0",LEFT('Raw Data'!K5,1),".", RIGHT('Raw Data'!K5,4)))) -> 43492 | L5: ='Raw Data'!L5 -> 0.85625 | M5: Ewallet | N5: =VALUE(IF(AND(ISERR(FIND(".",'Raw Data'!N5)),LEN('Raw Data'!N5)=5), IF(YEAR('Raw Data'!N5)=2026,CONCATENATE(DAY('Raw Data'!N5),".",IF(LEN(MONTH('Raw Data'!N5))=2,MONTH('Raw Data'!N5),CONCATENATE("0",MONTH('Raw Data'!N5)))),CONCATENATE(MONTH('Raw Data'!N5),".",RIGHT(YEAR('Raw Data'!N5),2))),'Raw Data'!N5)) -> 465.76 | O5: =P5/J5*100 -> 4.7619048 | P5: =J5-N5 -> 23.288 | Q5: =VALUE(IF(AND(ISERR(FIND(".",'Raw Data'!Q5)),LEN('Raw Data'!Q5)=5), IF(YEAR('Raw Data'!Q5)=2026,CONCATENATE(DAY('Raw Data'!Q5),".",IF(LEN(MONTH('Raw Data'!Q5))=2,MONTH('Raw Data'!Q5),CONCATENATE(MONTH('Raw Data'!Q5)))),CONCATENATE(MONTH('Raw Data'!Q5),".",RIGHT(YEAR('Raw Data'!Q5),2))),'Raw Data'!Q5)) -> 8.4
A6: 373-73-7910 | B6: A | C6: Yangon | D6: Normal | E6: Male | F6: Sports and travel | G6: =VALUE(IF(AND(ISERR(FIND(".",'Raw Data'!G6)),LEN('Raw Data'!G6)=5), IF(YEAR('Raw Data'!G6)=2026,CONCATENATE(DAY('Raw Data'!G6),".",IF(LEN(MONTH('Raw Data'!G6))=2,MONTH('Raw Data'!G6),CONCATENATE("0",MONTH('Raw Data'!G6)))),CONCATENATE(MONTH('Raw Data'!G6),".",RIGHT(YEAR('Raw Data'!G6),2))),'Raw Data'!G6)) -> 86.31 | H6: ='Raw Data'!H6 -> 7 | I6: =J6-G6*H6 -> 30.2085 | J6: ='Raw Data'!J6 -> 634.3785 | K6: =VALUE(IFERROR(VALUE('Raw Data'!K6),CONCATENATE(MID('Raw Data'!K6,3,2),".","0",LEFT('Raw Data'!K6,1),".", RIGHT('Raw Data'!K6,4)))) -> 43679 | L6: ='Raw Data'!L6 -> 0.44236111 | M6: Ewallet | N6: =VALUE(IF(AND(ISERR(FIND(".",'Raw Data'!N6)),LEN('Raw Data'!N6)=5), IF(YEAR('Raw Data'!N6)=2026,CONCATENATE(DAY('Raw Data'!N6),".",IF(LEN(MONTH('Raw Data'!N6))=2,MONTH('Raw Data'!N6),CONCATENATE("0",MONTH('Raw Data'!N6)))),CONCATENATE(MONTH('Raw Data'!N6),".",RIGHT(YEAR('Raw Data'!N6),2))),'Raw Data'!N6)) -> 604.17 | O6: =P6/J6*100 -> 4.7619048 | P6: =J6-N6 -> 30.2085 | Q6: =VALUE(IF(AND(ISERR(FIND(".",'Raw Data'!Q6)),LEN('Raw Data'!Q6)=5), IF(YEAR('Raw Data'!Q6)=2026,CONCATENATE(DAY('Raw Data'!Q6),".",IF(LEN(MONTH('Raw Data'!Q6))=2,MONTH('Raw Data'!Q6),CONCATENATE(MONTH('Raw Data'!Q6)))),CONCATENATE(MONTH('Raw Data'!Q6),".",RIGHT(YEAR('Raw Data'!Q6),2))),'Raw Data'!Q6)) -> 5.3
A7: 699-14-3026 | B7: C | C7: Naypyitaw | D7: Normal | E7: Male | F7: Electronic accessories | G7: =VALUE(IF(AND(ISERR(FIND(".",'Raw Data'!G7)),LEN('Raw Data'!G7)=5), IF(YEAR('Raw Data'!G7)=2026,CONCATENATE(DAY('Raw Data'!G7),".",IF(LEN(MONTH('Raw Data'!G7))=2,MONTH('Raw Data'!G7),CONCATENATE("0",MONTH('Raw Data'!G7)))),CONCATENATE(MONTH('Raw Data'!G7),".",RIGHT(YEAR('Raw Data'!G7),2))),'Raw Data'!G7)) -> 85.39 | H7: ='Raw Data'!H7 -> 7 | I7: =J7-G7*H7 -> 29.8865 | J7: ='Raw Data'!J7 -> 627.6165 | K7: =VALUE(IFERROR(VALUE('Raw Data'!K7),CONCATENATE(MID('Raw Data'!K7,3,2),".","0",LEFT('Raw Data'!K7,1),".", RIGHT('Raw Data'!K7,4)))) -> 43549 | L7: ='Raw Data'!L7 -> 0.77083333 | M7: Ewallet | N7: =VALUE(IF(AND(ISERR(FIND(".",'Raw Data'!N7)),LEN('Raw Data'!N7)=5), IF(YEAR('Raw Data'!N7)=2026,CONCATENATE(DAY('Raw Data'!N7),".",IF(LEN(MONTH('Raw Data'!N7))=2,MONTH('Raw Data'!N7),CONCATENATE("0",MONTH('Raw Data'!N7)))),CONCATENATE(MONTH('Raw Data'!N7),".",RIGHT(YEAR('Raw Data'!N7),2))),'Raw Data'!N7)) -> 597.73 | O7: =P7/J7*100 -> 4.7619048 | P7: =J7-N7 -> 29.8865 | Q7: =VALUE(IF(AND(ISERR(FIND(".",'Raw Data'!Q7)),LEN('Raw Data'!Q7)=5), IF(YEAR('Raw Data'!Q7)=2026,CONCATENATE(DAY('Raw Data'!Q7),".",IF(LEN(MONTH('Raw Data'!Q7))=2,MONTH('Raw Data'!Q7),CONCATENATE(MONTH('Raw Data'!Q7)))),CONCATENATE(MONTH('Raw Data'!Q7),".",RIGHT(YEAR('Raw Data'!Q7),2))),'Raw Data'!Q7)) -> 4.1
A8: 355-53-5943 | B8: A | C8: Yangon | D8: Member | E8: Female | F8: Electronic accessories | G8: =VALUE(IF(AND(ISERR(FIND(".",'Raw Data'!G8)),LEN('Raw Data'!G8)=5), IF(YEAR('Raw Data'!G8)=2026,CONCATENATE(DAY('Raw Data'!G8),".",IF(LEN(MONTH('Raw Data'!G8))=2,MONTH('Raw Data'!G8),CONCATENATE("0",MONTH('Raw Data'!G8)))),CONCATENATE(MONTH('Raw Data'!G8),".",RIGHT(YEAR('Raw Data'!G8),2))),'Raw Data'!G8)) -> 68.84 | H8: ='Raw Data'!H8 -> 6 | I8: =J8-G8*H8 -> 20.652 | J8: ='Raw Data'!J8 -> 433.692 | K8: =VALUE(IFERROR(VALUE('Raw Data'!K8),CONCATENATE(MID('Raw Data'!K8,3,2),".","0",LEFT('Raw Data'!K8,1),".", RIGHT('Raw Data'!K8,4)))) -> 43521 | L8: ='Raw Data'!L8 -> 0.60833333 | M8: Ewallet | N8: =VALUE(IF(AND(ISERR(FIND(".",'Raw Data'!N8)),LEN('Raw Data'!N8)=5), IF(YEAR('Raw Data'!N8)=2026,CONCATENATE(DAY('Raw Data'!N8),".",IF(LEN(MONTH('Raw Data'!N8))=2,MONTH('Raw Data'!N8),CONCATENATE("0",MONTH('Raw Data'!N8)))),CONCATENATE(MONTH('Raw Data'!N8),".",RIGHT(YEAR('Raw Data'!N8),2))),'Raw Data'!N8)) -> 413.04 | O8: =P8/J8*100 -> 4.7619048 | P8: =J8-N8 -> 20.652 | Q8: =VALUE(IF(AND(ISERR(FIND(".",'Raw Data'!Q8)),LEN('Raw Data'!Q8)=5), IF(YEAR('Raw Data'!Q8)=2026,CONCATENATE(DAY('Raw Data'!Q8),".",IF(LEN(MONTH('Raw Data'!Q8))=2,MONTH('Raw Data'!Q8),CONCATENATE(MONTH('Raw Data'!Q8)))),CONCATENATE(MONTH('Raw Data'!Q8),".",RIGHT(YEAR('Raw Data'!Q8),2))),'Raw Data'!Q8)) -> 5.8
A9: 315-22-5665 | B9: C | C9: Naypyitaw | D9: Normal | E9: Female | F9: Home and lifestyle | G9: =VALUE(IF(AND(ISERR(FIND(".",'Raw Data'!G9)),LEN('Raw Data'!G9)=5), IF(YEAR('Raw Data'!G9)=2026,CONCATENATE(DAY('Raw Data'!G9),".",IF(LEN(MONTH('Raw Data'!G9))=2,MONTH('Raw Data'!G9),CONCATENATE("0",MONTH('Raw Data'!G9)))),CONCATENATE(MONTH('Raw Data'!G9),".",RIGHT(YEAR('Raw Data'!G9),2))),'Raw Data'!G9)) -> 73.56 | H9: ='Raw Data'!H9 -> 10 | I9: =J9-G9*H9 -> 36.78 | J9: ='Raw Data'!J9 -> 772.38 | K9: =VALUE(IFERROR(VALUE('Raw Data'!K9),CONCATENATE(MID('Raw Data'!K9,3,2),".","0",LEFT('Raw Data'!K9,1),".", RIGHT('Raw Data'!K9,4)))) -> 43520 | L9: ='Raw Data'!L9 -> 0.48472222 | M9: Ewallet | N9: =VALUE(IF(AND(ISERR(FIND(".",'Raw Data'!N9)),LEN('Raw Data'!N9)=5), IF(YEAR('Raw Data'!N9)=2026,CONCATENATE(DAY('Raw Data'!N9),".",IF(LEN(MONTH('Raw Data'!N9))=2,MONTH('Raw Data'!N9),CONCATENATE("0",MONTH('Raw Data'!N9)))),CONCATENATE(MONTH('Raw Data'!N9),".",RIGHT(YEAR('Raw Data'!N9),2))),'Raw Data'!N9)) -> 735.6 | O9: =P9/J9*100 -> 4.7619048 | P9: =J9-N9 -> 36.78 | Q9: =VALUE(IF(AND(ISERR(FIND(".",'Raw Data'!Q9)),LEN('Raw Data'!Q9)=5), IF(YEAR('Raw Data'!Q9)=2026,CONCATENATE(DAY('Raw Data'!Q9),".",IF(LEN(MONTH('Raw Data'!Q9))=2,MONTH('Raw Data'!Q9),CONCATENATE(MONTH('Raw Data'!Q9)))),CONCATENATE(MONTH('Raw Data'!Q9),".",RIGHT(YEAR('Raw Data'!Q9),2))),'Raw Data'!Q9)) -> 8
A10: 665-32-9167 | B10: A | C10: Yangon | D10: Member | E10: Female | F10: Health and beauty | G10: =VALUE(IF(AND(ISERR(FIND(".",'Raw Data'!G10)),LEN('Raw Data'!G10)=5), IF(YEAR('Raw Data'!G10)=2026,CONCATENATE(DAY('Raw Data'!G10),".",IF(LEN(MONTH('Raw Data'!G10))=2,MONTH('Raw Data'!G10),CONCATENATE("0",MONTH('Raw Data'!G10)))),CONCATENATE(MONTH('Raw Data'!G10),".",RIGHT(YEAR('Raw Data'!G10),2))),'Raw Data'!G10)) -> 36.26 | H10: ='Raw Data'!H10 -> 2 | I10: =J10-G10*H10 -> 3.626 | J10: ='Raw Data'!J10 -> 76.146 | K10: =VALUE(IFERROR(VALUE('Raw Data'!K10),CONCATENATE(MID('Raw Data'!K10,3,2),".","0",LEFT('Raw Data'!K10,1),".", RIGHT('Raw Data'!K10,4)))) -> 43739 | L10: ='Raw Data'!L10 -> 0.71875 | M10: Credit card | N10: =VALUE(IF(AND(ISERR(FIND(".",'Raw Data'!N10)),LEN('Raw Data'!N10)=5), IF(YEAR('Raw Data'!N10)=2026,CONCATENATE(DAY('Raw Data'!N10),".",IF(LEN(MONTH('Raw Data'!N10))=2,MONTH('Raw Data'!N10),CONCATENATE("0",MONTH('Raw Data'!N10)))),CONCATENATE(MONTH('Raw Data'!N10),".",RIGHT(YEAR('Raw Data'!N10),2))),'Raw Data'!N10)) -> 72.52 | O10: =P10/J10*100 -> 4.7619048 | P10: =J10-N10 -> 3.626 | Q10: =VALUE(IF(AND(ISERR(FIND(".",'Raw Data'!Q10)),LEN('Raw Data'!Q10)=5), IF(YEAR('Raw Data'!Q10)=2026,CONCATENATE(DAY('Raw Data'!Q10),".",IF(LEN(MONTH('Raw Data'!Q10))=2,MONTH('Raw Data'!Q10),CONCATENATE(MONTH('Raw Data'!Q10)))),CONCATENATE(MONTH('Raw Data'!Q10),".",RIGHT(YEAR('Raw Data'!Q10),2))),'Raw Data'!Q10)) -> 7.2
A11: 692-92-5582 | B11: B | C11: Mandalay | D11: Member | E11: Female | F11: Food and beverages | G11: =VALUE(IF(AND(ISERR(FIND(".",'Raw Data'!G11)),LEN('Raw Data'!G11)=5), IF(YEAR('Raw Data'!G11)=2026,CONCATENATE(DAY('Raw Data'!G11),".",IF(LEN(MONTH('Raw Data'!G11))=2,MONTH('Raw Data'!G11),CONCATENATE("0",MONTH('Raw Data'!G11)))),CONCATENATE(MONTH('Raw Data'!G11),".",RIGHT(YEAR('Raw Data'!G11),2))),'Raw Data'!G11)) -> 54.84 | H11: ='Raw Data'!H11 -> 3 | I11: =J11-G11*H11 -> 8.226 | J11: ='Raw Data'!J11 -> 172.746 | K11: =VALUE(IFERROR(VALUE('Raw Data'!K11),CONCATENATE(MID('Raw Data'!K11,3,2),".","0",LEFT('Raw Data'!K11,1),".", RIGHT('Raw Data'!K11,4)))) -> 43516 | L11: ='Raw Data'!L11 -> 0.56041667 | M11: Credit card | N11: =VALUE(IF(AND(ISERR(FIND(".",'Raw Data'!N11)),LEN('Raw Data'!N11)=5), IF(YEAR('Raw Data'!N11)=2026,CONCATENATE(DAY('Raw Data'!N11),".",IF(LEN(MONTH('Raw Data'!N11))=2,MONTH('Raw Data'!N11),CONCATENATE("0",MONTH('Raw Data'!N11)))),CONCATENATE(MONTH('Raw Data'!N11),".",RIGHT(YEAR('Raw Data'!N11),2))),'Raw Data'!N11)) -> 164.52 | O11: =P11/J11*100 -> 4.7619048 | P11: =J11-N11 -> 8.226 | Q11: =VALUE(IF(AND(ISERR(FIND(".",'Raw Data'!Q11)),LEN('Raw Data'!Q11)=5), IF(YEAR('Raw Data'!Q11)=2026,CONCATENATE(DAY('Raw Data'!Q11),".",IF(LEN(MONTH('Raw Data'!Q11))=2,MONTH('Raw Data'!Q11),CONCATENATE(MONTH('Raw Data'!Q11)))),CONCATENATE(MONTH('Raw Data'!Q11),".",RIGHT(YEAR('Raw Data'!Q11),2))),'Raw Data'!Q11)) -> 5.9
A12: 351-62-0822 | B12: B | C12: Mandalay | D12: Member | E12: Female | F12: Fashion accessories | G12: =VALUE(IF(AND(ISERR(FIND(".",'Raw Data'!G12)),LEN('Raw Data'!G12)=5), IF(YEAR('Raw Data'!G12)=2026,CONCATENATE(DAY('Raw Data'!G12),".",IF(LEN(MONTH('Raw Data'!G12))=2,MONTH('Raw Data'!G12),CONCATENATE("0",MONTH('Raw Data'!G12)))),CONCATENATE(MONTH('Raw Data'!G12),".",RIGHT(YEAR('Raw Data'!G12),2))),'Raw Data'!G12)) -> 14.48 | H12: ='Raw Data'!H12 -> 4 | I12: =J12-G12*H12 -> 2.896 | J12: ='Raw Data'!J12 -> 60.816 | K12: =VALUE(IFERROR(VALUE('Raw Data'!K12),CONCATENATE(MID('Raw Data'!K12,3,2),".","0",LEFT('Raw Data'!K12,1),".", RIGHT('Raw Data'!K12,4)))) -> 43618 | L12: ='Raw Data'!L12 -> 0.75486111 | M12: Ewallet | N12: =VALUE(IF(AND(ISERR(FIND(".",'Raw Data'!N12)),LEN('Raw Data'!N12)=5), IF(YEAR('Raw Data'!N12)=2026,CONCATENATE(DAY('Raw Data'!N12),".",IF(LEN(MONTH('Raw Data'!N12))=2,MONTH('Raw Data'!N12),CONCATENATE("0",MONTH('Raw Data'!N12)))),CONCATENATE(MONTH('Raw Data'!N12),".",RIGHT(YEAR('Raw Data'!N12),2))),'Raw Data'!N12)) -> 57.92 | O12: =P12/J12*100 -> 4.7619048 | P12: =J12-N12 -> 2.896 | Q12: =VALUE(IF(AND(ISERR(FIND(".",'Raw Data'!Q12)),LEN('Raw Data'!Q12)=5), IF(YEAR('Raw Data'!Q12)=2026,CONCATENATE(DAY('Raw Data'!Q12),".",IF(LEN(MONTH('Raw Data'!Q12))=2,MONTH('Raw Data'!Q12),CONCATENATE(MONTH('Raw Data'!Q12)))),CONCATENATE(MONTH('Raw Data'!Q12),".",RIGHT(YEAR('Raw Data'!Q12),2))),'Raw Data'!Q12)) -> 4.5
A13: 529-56-3974 | B13: B | C13: Mandalay | D13: Member | E13: Male | F13: Electronic accessories | G13: =VALUE(IF(AND(ISERR(FIND(".",'Raw Data'!G13)),LEN('Raw Data'!G13)=5), IF(YEAR('Raw Data'!G13)=2026,CONCATENATE(DAY('Raw Data'!G13),".",IF(LEN(MONTH('Raw Data'!G13))=2,MONTH('Raw Data'!G13),CONCATENATE("0",MONTH('Raw Data'!G13)))),CONCATENATE(MONTH('Raw Data'!G13),".",RIGHT(YEAR('Raw Data'!G13),2))),'Raw Data'!G13)) -> 25.51 | H13: ='Raw Data'!H13 -> 4 | I13: =J13-G13*H13 -> 5.102 | J13: ='Raw Data'!J13 -> 107.142 | K13: =VALUE(IFERROR(VALUE('Raw Data'!K13),CONCATENATE(MID('Raw Data'!K13,3,2),".","0",LEFT('Raw Data'!K13,1),".", RIGHT('Raw Data'!K13,4)))) -> 43711 | L13: ='Raw Data'!L13 -> 0.71041667 | M13: Cash | N13: =VALUE(IF(AND(ISERR(FIND(".",'Raw Data'!N13)),LEN('Raw Data'!N13)=5), IF(YEAR('Raw Data'!N13)=2026,CONCATENATE(DAY('Raw Data'!N13),".",IF(LEN(MONTH('Raw Data'!N13))=2,MONTH('Raw Data'!N13),CONCATENATE("0",MONTH('Raw Data'!N13)))),CONCATENATE(MONTH('Raw Data'!N13),".",RIGHT(YEAR('Raw Data'!N13),2))),'Raw Data'!N13)) -> 102.04 | O13: =P13/J13*100 -> 4.7619048 | P13: =J13-N13 -> 5.102 | Q13: =VALUE(IF(AND(ISERR(FIND(".",'Raw Data'!Q13)),LEN('Raw Data'!Q13)=5), IF(YEAR('Raw Data'!Q13)=2026,CONCATENATE(DAY('Raw Data'!Q13),".",IF(LEN(MONTH('Raw Data'!Q13))=2,MONTH('Raw Data'!Q13),CONCATENATE(MONTH('Raw Data'!Q13)))),CONCATENATE(MONTH('Raw Data'!Q13),".",RIGHT(YEAR('Raw Data'!Q13),2))),'Raw Data'!Q13)) -> 6.8
... A1001: 849-09-3807 | B1001: A | C1001: Yangon | D1001: Member | E1001: Female | F1001: Fashion accessories | G1001: =VALUE(IF(AND(ISERR(FIND(".",'Raw Data'!G1001)),LEN('Raw Data'!G1001)=5), IF(YEAR('Raw Data'!G1001)=2026,CONCATENATE(DAY('Raw Data'!G1001),".",IF(LEN(MONTH('Raw Data'!G1001))=2,MONTH('Raw Data'!G1001),CONCATENATE("0",MONTH('Raw Data'!G1001)))),CONCATENATE(MONTH('Raw Data'!G1001),".",RIGHT(YEAR('Raw Data'!G1001),2))),'Raw Data'!G1001)) -> 88.34 | H1001: ='Raw Data'!H1001 -> 7 | I1001: =J1001-G1001*H1001 -> 30.919 | J1001: ='Raw Data'!J1001 -> 649.299 | K1001: =VALUE(IFERROR(VALUE('Raw Data'!K1001),CONCATENATE(MID('Raw Data'!K1001,3,2),".","0",LEFT('Raw Data'!K1001,1),".", RIGHT('Raw Data'!K1001,4)))) -> 43514 | L1001: ='Raw Data'!L1001 -> 0.56111111 | M1001: Cash | N1001: =VALUE(IF(AND(ISERR(FIND(".",'Raw Data'!N1001)),LEN('Raw Data'!N1001)=5), IF(YEAR('Raw Data'!N1001)=2026,CONCATENATE(DAY('Raw Data'!N1001),".",IF(LEN(MONTH('Raw Data'!N1001))=2,MONTH('Raw Data'!N1001),CONCATENATE("0",MONTH('Raw Data'!N1001)))),CONCATENATE(MONTH('Raw Data'!N1001),".",RIGHT(YEAR('Raw Data'!N1001),2))),'Raw Data'!N1001)) -> 618.38 | O1001: =P1001/J1001*100 -> 4.7619048 | P1001: =J1001-N1001 -> 30.919 | Q1001: =VALUE(IF(AND(ISERR(FIND(".",'Raw Data'!Q1001)),LEN('Raw Data'!Q1001)=5), IF(YEAR('Raw Data'!Q1001)=2026,CONCATENATE(DAY('Raw Data'!Q1001),".",IF(LEN(MONTH('Raw Data'!Q1001))=2,MONTH('Raw Data'!Q1001),CONCATENATE(MONTH('Raw Data'!Q1001)))),CONCATENATE(MONTH('Raw Data'!Q1001),".",RIGHT(YEAR('Raw Data'!Q1001),2))),'Raw Data'!Q1001)) -> 6.6

Sheet Pivot Tables
A1: Анализ по гендеру: | F1: Обобщенно: | I1: Анализ по типу клиента:
A3: Общая выручка | B3: Gender | F3: Общая выручка по гендеру | I3: Общая выручка по типу клиента
A4: Product line | B4: Female | C4: Male | D4: Общий итог | F4: Gender | G4: Итог | I4: Customer type | J4: Итог
A5: Electronic accessories | B5: 27102.022 | C5: 27235.509 | D5: 54337.531 | F5: Female | G5: 184642.23 | I5: Member | J5: 501
A6: Fashion accessories | B6: 47196.706 | C6: 23868.495 | D6: 71065.201 | F6: Male | G6: 186394.15 | I6: Normal | J6: 499
A7: Food and beverages | B7: 33170.917 | C7: 22973.926 | D7: 56144.844 | F7: Общий итог | G7: 371036.38 | I7: Общий итог | J7: 1000
A8: Health and beauty | B8: 18560.986 | C8: 30632.752 | D8: 49193.739
A9: Home and lifestyle | B9: 30036.878 | C9: 23825.035 | D9: 53861.913
A10: Sports and travel | B10: 28574.721 | C10: 57858.427 | D10: 86433.148
A11: Общий итог | B11: 184642.23 | C11: 186394.15 | D11: 371036.38
A13: Анализ прибыльности компании по категории товара: | F13: Анализ каналов продаж (город и филиал):
B15: Значения | G15: Значения | K15: Значения
A16: Product line | B16: Общая выручка | C16: Общая себестоимость | D16: Общая прибыль | F16: City | G16: Кол-во товаров | H16: Общая прибыль | J16: Branch | K16: Кол-во товаров | L16: Общая прибыль
A17: Electronic accessories | B17: 54337.532 | C17: 51750.03 | D17: 2587.5015 | F17: Mandalay | G17: 1820 | H17: 5057.032 | J17: A | K17: 1859 | L17: 21817.546
A18: Fashion accessories | B18: 71065.2 | C18: 51718.82 | D18: 19346.38 | F18: Naypyitaw | G18: 1831 | H18: 36575.498 | J18: B | K18: 1820 | L18: 5057.032
A19: Food and beverages | B19: 56144.844 | C19: 53471.28 | D19: 2673.564 | F19: Yangon | G19: 1859 | H19: 21817.546 | J19: C | K19: 1831 | L19: 36575.498
A20: Health and beauty | B20: 49193.739 | C20: 46851.18 | D20: 2342.559 | F20: Общий итог | G20: 5510 | H20: 63450.076 | J20: Общий итог | K20: 5510 | L20: 63450.076
A21: Home and lifestyle | B21: 53861.913 | C21: 51297.06 | D21: 2564.853
A22: Sports and travel | B22: 86433.148 | C22: 52497.93 | D22: 33935.218
A23: Общий итог | B23: 371036.38 | C23: 307586.3 | D23: 63450.076
A25: Анализ способов оплаты: | F25: Анализ времени продаж: | J25: Анализ сезонности продаж:
A27: Количество клиентов | F27: Общая выручка | J27: Общая выручка
A28: Payment | B28: Итог | F28: Часы | G28: Time | H28: Итог | J28: Месяцы | K28: Итог
A29: Cash | B29: 344 | F29: 10 | H29: 31421.481 | J29: янв | K29: 103321.87
A30: Credit card | B30: 311 | F30: 11 | H30: 30377.329 | J30: фев | K30: 63169.743
A31: Ewallet | B31: 345 | F31: 12 | H31: 26065.882 | J31: мар | K31: 72749.25
A32: Общий итог | B32: 1000 | F32: 13 | H32: 34723.227 | J32: апр | K32: 7957.6245
F33: 14 | H33: 62138.721 | J33: май | K33: 12798.692
F34: 15 | H34: 31179.508 | J34: июн | K34: 9612.225
F35: 16 | H35: 25226.323 | J35: июл | K35: 42811.035
F36: 17 | H36: 24445.218 | J36: авг | K36: 13503.777
F37: 18 | H37: 42789.645 | J37: сен | K37: 13767.285
F38: 19 | H38: 39699.513 | J38: окт | K38: 9865.2015
F39: 20 | H39: 22969.527 | J39: ноя | K39: 9618.3675
F40: Общий итог | H40: 371036.38 | J40: дек | K40: 11861.304
J41: Общий итог | K41: 371036.38

Sheet Dashboard
A1: Анализ продаж супермаркета за 2019
A3: Анализ продаж по категориям товаров, регионам, времени и способам оплаты. Данные содержат 1000+ транзакций.
A5: Ключевые выводы:
A7: 1. Гендерный анализ
A8: Мужчины и женщины приносят практически равную выручку (разница 0,5%). Мужчины предпочитают категорию "Sports and travel" (16% продаж), женщины — "Fashion accessories" (13%).
A10: Рекомендации: Сегментировать рекламные кампании, продвигая спорт и путешествия мужчинам, аксессуары — женщинам.
A43: 2. Товарная прибыльность
A44: Наибольшую прибыль дают "Sports and travel" и "Fashion accessories". У категории "Food and beverages" высокая выручка, но самая высокая себестоимость.
A46: Рекомендации: Пересмотреть закупочные цены на "Food and beverages", чтобы увеличить прибыль. Категорию "Health and beauty" (низкая прибыль) использовать как "якорную" для привлечения потока.
A65: 3. Регионы
A66: Город Naypyitaw — самый прибыльный (как и Yangon). Mandalay проваливается по выручке (в 7 раз ниже при том же количестве товара).
A68: Рекомендации: Проверить ценообразование в Mandalay: возможно, там слишком низкие цены или идут массовые распродажи.
... A168: 3. Усилить маркетинг в декабре под январский пик.
